social_login/__init__.py
social_login/run_example.py
social_login/backends/__init__.py
social_login/backends/apple.py
social_login/backends/constants.py
social_login/backends/google.py
social_login/backends/oauth_models.py
social_login/example/__init__.py
social_login/example/app.py
py_social_login-0.0.3.dist-info/METADATA
py_social_login-0.0.3.dist-info/WHEEL
py_social_login-0.0.3.dist-info/top_level.txt
py_social_login-0.0.3.dist-info/RECORD
