Metadata-Version: 2.1
Name: py_social_login
Version: 0.0.3
Summary: Py Social Login
Home-page: https://github.com/udaykrishna/py-social-login/
Author: Uday Krishna
Author-email: uday@udaykrishna.com
Classifier: Programming Language :: Python :: 3
Classifier: Operating System :: OS Independent
Requires-Python: >=3.9
Requires-Dist: PyJWT
Requires-Dist: cryptography
Requires-Dist: pydantic
Requires-Dist: pytz
Requires-Dist: requests
Provides-Extra: dev
Requires-Dist: flask; extra == "dev"
